git_python_utils/__init__.py
git_python_utils/author.py
git_python_utils/author_stats.py
git_python_utils/changelog.py
git_python_utils/git_repo.py
git_python_utils/utils.py
git_python_utils/version.py
git_python_utils/version_string.py
git_python_utils-0.5.dist-info/DESCRIPTION.rst
git_python_utils-0.5.dist-info/METADATA
git_python_utils-0.5.dist-info/RECORD
git_python_utils-0.5.dist-info/WHEEL
git_python_utils-0.5.dist-info/entry_points.txt
git_python_utils-0.5.dist-info/metadata.json
git_python_utils-0.5.dist-info/top_level.txt
