Metadata-Version: 2.0
Name: git-python-utils
Version: 0.5
Summary: A collection of command-line utilities for interacting with git repositories
Home-page: http://github.com/eriknyquist/git_python_utils
Author: Erik Nyquist
Author-email: eknyquist@gmail.com
License: Apache 2.0
Platform: UNKNOWN
Requires-Dist: gitpython
